universal_mcp_spotify/README.md
universal_mcp_spotify/__init__.py
universal_mcp_spotify/app.py
universal_mcp_spotify/mcp.py
universal_mcp_spotify-0.1.1.dist-info/METADATA
universal_mcp_spotify-0.1.1.dist-info/WHEEL
universal_mcp_spotify-0.1.1.dist-info/entry_points.txt
universal_mcp_spotify-0.1.1.dist-info/licenses/LICENSE
universal_mcp_spotify-0.1.1.dist-info/RECORD
